README.rst
setup.py
mpho.egg-info/PKG-INFO
mpho.egg-info/SOURCES.txt
mpho.egg-info/dependency_links.txt
mpho.egg-info/top_level.txt
pho/__init__.py
pho/cli.py
scripts/pho