Metadata-Version: 1.1
Name: mpho
Version: 0.3.0
Summary: PytHon utility for Organizing tasks
Home-page: https://github.com/hvnsweeting/pho
Author: Viet Hung Nguyen
Author-email: hvn@familug.org
License: MIT
Platform: UNKNOWN
Classifier: Environment :: Console
Classifier: Topic :: Terminals :: Terminal Emulators/X Terminals
